vttdiff.py
vttdiff-0.0.3.dist-info/METADATA
vttdiff-0.0.3.dist-info/WHEEL
vttdiff-0.0.3.dist-info/entry_points.txt
vttdiff-0.0.3.dist-info/licenses/LICENSE
vttdiff-0.0.3.dist-info/RECORD
