Metadata-Version: 2.4
Name: vttdiff
Version: 0.0.3
Summary: Create a HTML "diff" ebVTT files
Project-URL: homepage, https://github.com/edsu/vttdiff
License-File: LICENSE
Requires-Python: >=3.11
Requires-Dist: beautifulsoup4>=4.13.3
